LICENSE.bsd
MANIFEST.in
README.rst
setup.py
docs/Makefile
docs/conf.py
docs/index.rst
src/rtd.py
src/rtd.egg-info/PKG-INFO
src/rtd.egg-info/SOURCES.txt
src/rtd.egg-info/dependency_links.txt
src/rtd.egg-info/entry_points.txt
src/rtd.egg-info/requires.txt
src/rtd.egg-info/top_level.txt
src/rtd.egg-info/zip-safe