Metadata-Version: 1.0
Name: rtd
Version: 1.2.3
Summary: Find documentation on Read the Docs!
Home-page: http://github.com/ericholscher/rtd
Author: Eric Holscher
Author-email: eric@ericholscher.com
License: BSD
Platform: UNKNOWN
